{
  "orders": [
    {
      "id": "ORD1752313460378653",
      "trackingNumber": "TRK20250712790",
      "customerName": "Jane Smith",
      "customerEmail": "jane.smith@example.com",
      "customerPhone": "(555) 987-6543",
      "pickupAddress": "789 Pine St, Chicago, IL 60601",
      "deliveryAddress": "321 Elm St, Miami, FL 33101",
      "packageDetails": {
        "weight": "8",
        "dimensions": "25x20x15",
        "description": "Electronics",
        "quantity": 1
      },
      "serviceType": "Express Delivery",
      "status": "Order Placed",
      "currentStage": "Order Placed",
      "stages": [
        {
          "stage": "Order Placed",
          "timestamp": "2025-07-12T09:44:20.378Z",
          "location": "Online",
          "description": "Order received and confirmed"
        },
        {
          "stage": "Package Picked Up",
          "timestamp": "2025-07-12T11:32:24.853Z",
          "location": "Online",
          "description": "Order received and confirmed"
        },
        {
          "stage": "Delivered",
          "timestamp": "2025-07-12T15:44:40.785Z",
          "location": "Online",
          "description": "Order received and confirmed"
        },
        {
          "stage": "Failed Delivery",
          "timestamp": "2025-07-12T21:06:29.188Z",
          "location": "Online",
          "description": "Order received and confirmed"
        },
        {
          "timestamp": "2025-07-17T11:12:55.275Z",
          "location": "Processing Center",
          "description": "Order status updated to Order Placed",
          "stage": "Order Placed"
        }
      ],
      "estimatedDelivery": "2025-07-14T16:00:00.000Z",
      "actualDelivery": "2025-07-12T15:44:40.785Z",
      "price": 325,
      "createdAt": "2025-07-12T09:44:20.379Z",
      "updatedAt": "2025-07-17T11:12:55.275Z"
    },
    {
      "id": "ORD1752313699262752",
      "trackingNumber": "TRK20250712430",
      "customerName": "Real Time Test",
      "customerEmail": "realtime@test.com",
      "customerPhone": "555-999-8888",
      "pickupAddress": "999 Test Blvd, Test City, TC 99999",
      "deliveryAddress": "888 Test Lane, Test Town, TT 88888",
      "packageDetails": {
        "weight": "12",
        "dimensions": "35x25x18",
        "description": "Real-time test package",
        "quantity": 1
      },
      "serviceType": "Express Delivery",
      "status": "Out for Delivery",
      "currentStage": "Out for Delivery",
      "stages": [
        {
          "stage": "Order Placed",
          "timestamp": "2025-07-12T09:48:19.263Z",
          "location": "Online",
          "description": "Order received and confirmed"
        },
        {
          "stage": "Out for Delivery",
          "timestamp": "2025-07-12T11:32:46.311Z",
          "location": "Online",
          "description": "Order received and confirmed"
        },
        {
          "stage": "In Transit",
          "timestamp": "2025-07-12T15:44:24.680Z",
          "location": "Online",
          "description": "Order received and confirmed"
        },
        {
          "timestamp": "2025-07-17T11:13:25.213Z",
          "location": "Processing Center",
          "description": "Order status updated to Out for Delivery",
          "stage": "Out for Delivery"
        }
      ],
      "estimatedDelivery": "2025-07-14T16:00:00.000Z",
      "actualDelivery": null,
      "price": 408,
      "createdAt": "2025-07-12T09:48:19.263Z",
      "updatedAt": "2025-07-17T11:13:25.213Z"
    },
    {
      "id": "ORD1752316309174709",
      "trackingNumber": "TRK20250712352",
      "customerName": "Miles Ella",
      "customerEmail": "keymaxestate@gmail.com",
      "customerPhone": "4258809587",
      "pickupAddress": "239, bremerton",
      "deliveryAddress": "apt 120",
      "packageDetails": {
        "weight": "56",
        "dimensions": "50x50x30",
        "description": "goods",
        "quantity": 1
      },
      "serviceType": "Express Delivery",
      "specialInstructions": "lagossdsdsfd",
      "status": "Order Placed",
      "currentStage": "Order Placed",
      "stages": [
        {
          "stage": "Order Placed",
          "timestamp": "2025-07-12T10:31:49.175Z",
          "location": "Online",
          "description": "Order received and confirmed"
        }
      ],
      "estimatedDelivery": "2025-07-14T16:00:00.000Z",
      "actualDelivery": null,
      "price": 1000,
      "createdAt": "2025-07-12T10:31:49.176Z",
      "updatedAt": "2025-07-12T10:31:49.176Z"
    },
    {
      "id": "ORD1752316841818437",
      "trackingNumber": "TRK20250712603",
      "customerName": "Thompson Opeyemi",
      "customerEmail": "Topeyemi33@gmail.com",
      "customerPhone": "4258809587",
      "pickupAddress": "181, Nasfat Street, Odogunyan ,Ikorodu",
      "deliveryAddress": "lagos",
      "packageDetails": {
        "weight": "45",
        "dimensions": "50x50x50",
        "description": "lagos",
        "quantity": 1
      },
      "serviceType": "Air Freight",
      "specialInstructions": "",
      "status": "Order Placed",
      "currentStage": "Order Placed",
      "stages": [
        {
          "stage": "Order Placed",
          "timestamp": "2025-07-12T10:40:41.818Z",
          "location": "Online",
          "description": "Order received and confirmed"
        }
      ],
      "estimatedDelivery": "2025-07-15T16:00:00.000Z",
      "actualDelivery": null,
      "price": 1650,
      "createdAt": "2025-07-12T10:40:41.818Z",
      "updatedAt": "2025-07-12T10:40:41.818Z"
    }
  ],
  "trackingStages": [
    "Order Placed",
    "Package Picked Up",
    "Out for Delivery",
    "In Transit",
    "Delivered",
    "Failed Delivery"
  ],
  "serviceTypes": [
    "Standard Delivery",
    "Express Delivery",
    "Air Freight",
    "Ocean Freight",
    "Ground Transport",
    "Same Day Delivery"
  ],
  "nextOrderId": 3,
  "nextTrackingNumber": 1003,
  "adminAccounts": [
    {
      "id": "ADM1701234567890",
      "firstName": "Admin",
      "lastName": "User",
      "email": "admin@yanglogistics.com",
      "phone": "+1-555-0123",
      "company": "YangLogistics",
      "role": "super_admin",
      "password": "Admin123!",
      "createdAt": "2024-12-01T10:00:00Z",
      "isActive": true
    }
  ]
}